axis_vapix/DoorControl.py
axis_vapix/GeolocationAPI.py
axis_vapix/PTZControl.py
axis_vapix/Schedule.py
axis_vapix/__init__.py
axis_vapix/api.py
axis_vapix/device.py
axis_vapix/py.typed
axis_vapix-0.1.10.dist-info/WHEEL
axis_vapix-0.1.10.dist-info/METADATA
axis_vapix-0.1.10.dist-info/RECORD
