Metadata-Version: 2.3
Name: axis-vapix
Version: 0.1.10
Summary: Library for interacting with the Axis VAPIX API
Author: Dark Decoy
Author-email: Dark Decoy <darkdecoy@notracking.space>
Requires-Dist: icalendar>=6.3.1
Requires-Dist: python-dateutil>=2.9.0.post0
Requires-Dist: requests>=2.32.5
Requires-Python: >=3.12
